chatmancy/__init__.py
chatmancy/agent/__init__.py
chatmancy/agent/base.py
chatmancy/agent/functions.py
chatmancy/agent/gpt/__init__.py
chatmancy/agent/gpt/agent.py
chatmancy/agent/gpt/history.py
chatmancy/agent/gpt/model.py
chatmancy/agent/history.py
chatmancy/agent/model.py
chatmancy/conversation/__init__.py
chatmancy/conversation/context_manager.py
chatmancy/conversation/conversation.py
chatmancy/function/__init__.py
chatmancy/function/function_item.py
chatmancy/function/function_message.py
chatmancy/function/generator.py
chatmancy/logging/__init__.py
chatmancy/logging/tracer.py
chatmancy/message/__init__.py
chatmancy/message/message.py
chatmancy-0.0.2.dist-info/METADATA
chatmancy-0.0.2.dist-info/WHEEL
chatmancy-0.0.2.dist-info/RECORD
