Metadata-Version: 2.1
Name: chatmancy
Version: 0.0.2
Summary: Agent, chat, conversation framework for interacting with LLMs.
Author: Caleb Case
Author-email: caleb.case93@gmail.com
Requires-Python: >=3.9,<4.0
Classifier: Programming Language :: Python :: 3
Classifier: Programming Language :: Python :: 3.9
Classifier: Programming Language :: Python :: 3.10
Classifier: Programming Language :: Python :: 3.11
Classifier: Programming Language :: Python :: 3.12
Requires-Dist: dill (>=0.3,<0.4)
Requires-Dist: flake8-pyproject (>=1.2.3,<2.0.0)
Requires-Dist: openai (>=1.8,<1.9)
Requires-Dist: opentelemetry-api (>=1.21,<1.22)
Requires-Dist: tenacity (>=8.2,<8.3)
Requires-Dist: tiktoken (>=0.5,<0.6)
